csv_reconcile_levenshtein/__init__.py
csv_reconcile_levenshtein-0.1.5.dist-info/entry_points.txt
csv_reconcile_levenshtein-0.1.5.dist-info/LICENSE
csv_reconcile_levenshtein-0.1.5.dist-info/WHEEL
csv_reconcile_levenshtein-0.1.5.dist-info/METADATA
csv_reconcile_levenshtein-0.1.5.dist-info/RECORD
